cyral_django_wrapper/__init__.py
cyral_django_wrapper/apps.py
cyral_django_wrapper/errors.py
cyral_django_wrapper/settings.py
cyral_django_wrapper-0.1.26.dist-info/WHEEL
cyral_django_wrapper-0.1.26.dist-info/METADATA
cyral_django_wrapper-0.1.26.dist-info/RECORD
